__init__.py
pymanifold.py
data/__init__.py
data/libdreal.so
data/__pycache__/__init__.cpython-36.pyc
data/dreal/__init__.py
data/dreal/__pycache__/__init__.cpython-36.pyc
data/dreal/api/__init__.py
data/dreal/api/_dreal_api_py.so
data/dreal/api/__pycache__/__init__.cpython-36.pyc
data/dreal/solver/__init__.py
data/dreal/solver/_dreal_solver_py.so
data/dreal/solver/__pycache__/__init__.cpython-36.pyc
data/dreal/symbolic/__init__.py
data/dreal/symbolic/_dreal_symbolic_py.so
data/dreal/symbolic/__pycache__/__init__.cpython-36.pyc
data/dreal/util/__init__.py
data/dreal/util/_dreal_util_py.so
data/dreal/util/__pycache__/__init__.cpython-36.pyc
pymanifold/__init__.py
pymanifold/pymanifold.py
pymanifold-0.2.3.dist-info/DESCRIPTION.rst
pymanifold-0.2.3.dist-info/METADATA
pymanifold-0.2.3.dist-info/RECORD
pymanifold-0.2.3.dist-info/WHEEL
pymanifold-0.2.3.dist-info/metadata.json
pymanifold-0.2.3.dist-info/top_level.txt
src/__init__.py
src/pymanifold.py
src/__pycache__/__init__.cpython-36.pyc
src/__pycache__/pymanifold.cpython-36.pyc
tests/Pipfile
tests/Pipfile.lock
tests/__init__.py
tests/dreal_test.py
tests/single_channel_test.py
tests/t_junction_test.py
