Metadata-Version: 2.0
Name: pymanifold
Version: 0.2.3
Summary: Python-Manifold is a Python implementation of Derek Rayside's    Manifold microfluidic simulation tool
Home-page: https://github.com/manifold-lang/pymanifold
Author: Josh Reid
Author-email: js2reid@uwaterloo.ca
License: GPLv3
Project-URL: Project, https://github.com/manifold-lang
Keywords: Python Manifold microfluidics simulation
Platform: UNKNOWN
Requires-Dist: matplotlib
Requires-Dist: networkx
